tiktok_research_api_helper/__init__.py
tiktok_research_api_helper/api_client.py
tiktok_research_api_helper/models.py
tiktok_research_api_helper/query.py
tiktok_research_api_helper/region_codes.py
tiktok_research_api_helper/utils.py
tiktok_research_api_helper/cli/custom_argument_types.py
tiktok_research_api_helper/cli/main.py
tiktok_research_api_helper-0.1.3.dist-info/METADATA
tiktok_research_api_helper-0.1.3.dist-info/WHEEL
tiktok_research_api_helper-0.1.3.dist-info/entry_points.txt
tiktok_research_api_helper-0.1.3.dist-info/RECORD
