Metadata-Version: 2.3
Name: tiktok_research_api_helper
Version: 0.1.3
Summary: A small package to interface with the TikTok Research API
Project-URL: Homepage, https://github.com/CybersecurityForDemocracy/tiktok-library
Project-URL: Issues, https://github.com/CybersecurityForDemocracy/tiktok-library/issues
Author-email: Bruno Coelho <bruno.coelho+c4d@nyu.edu>
Classifier: License :: OSI Approved :: MIT License
Classifier: Operating System :: OS Independent
Classifier: Programming Language :: Python :: 3
Requires-Python: >=3.11
Requires-Dist: attrs
Requires-Dist: certifi
Requires-Dist: numpy
Requires-Dist: pandas
Requires-Dist: pause
Requires-Dist: pendulum
Requires-Dist: psycopg2-binary
Requires-Dist: pyyaml
Requires-Dist: requests
Requires-Dist: rich
Requires-Dist: sqlalchemy>=2.0.0
Requires-Dist: tenacity
Requires-Dist: typer
